eight_mile/__init__.py
eight_mile/bleu.py
eight_mile/confusion.py
eight_mile/conlleval.py
eight_mile/downloads.py
eight_mile/embeddings.py
eight_mile/metrics.py
eight_mile/optz.py
eight_mile/progress.py
eight_mile/utils.py
eight_mile/version.py
eight_mile/calibration/__init__.py
eight_mile/calibration/calibration.py
eight_mile/calibration/metrics/__init__.py
eight_mile/calibration/metrics/calibration_error.py
eight_mile/calibration/plot/__init__.py
eight_mile/calibration/plot/confidence_histogram.py
eight_mile/calibration/plot/reliability_diagram.py
eight_mile/pytorch/__init__.py
eight_mile/pytorch/embeddings.py
eight_mile/pytorch/layers.py
eight_mile/pytorch/optz.py
eight_mile/pytorch/serialize.py
eight_mile/tf/__init__.py
eight_mile/tf/embeddings.py
eight_mile/tf/layers.py
eight_mile/tf/optz.py
eight_mile/tf/serialize.py
mead_layers-2.4.2.dist-info/LICENSE
mead_layers-2.4.2.dist-info/METADATA
mead_layers-2.4.2.dist-info/NOTICE
mead_layers-2.4.2.dist-info/WHEEL
mead_layers-2.4.2.dist-info/entry_points.txt
mead_layers-2.4.2.dist-info/top_level.txt
mead_layers-2.4.2.dist-info/RECORD
