Metadata-Version: 2.1
Name: mead-layers
Version: 2.4.2
Summary: Reusable Deep-Learning layers for NLP
Home-page: https://www.github.com/mead-ml/mead-layers
Author: mead-ml
Author-email: mead.baseline@gmail.com
License: Apache 2.0
Download-URL: https://www.github.com/mead-ml/mead-layers/archive/2.4.2.tar.gz
Keywords: deep-learning,nlp,pytorch,tensorflow
Platform: UNKNOWN
Classifier: Environment :: Console
Classifier: License :: OSI Approved :: Apache Software License
Classifier: Programming Language :: Python :: 3.6
Classifier: Natural Language :: English
Classifier: Programming Language :: Python :: 3.5
Classifier: Development Status :: 3 - Alpha
Classifier: Topic :: Scientific/Engineering :: Artificial Intelligence
Classifier: Programming Language :: Python :: 3.7
Classifier: Operating System :: OS Independent
Classifier: Intended Audience :: Developers
Classifier: Intended Audience :: Science/Research
License-File: ../LICENSE
License-File: ../NOTICE
Requires-Dist: numpy
Provides-Extra: plot
Requires-Dist: matplotlib ; extra == 'plot'
Provides-Extra: test
Requires-Dist: pytest ; extra == 'test'
Requires-Dist: mock ; extra == 'test'
Requires-Dist: contextdecorator ; extra == 'test'
Requires-Dist: pytest-forked ; extra == 'test'
Provides-Extra: tf2
Requires-Dist: tensorflow-addons ; extra == 'tf2'
Provides-Extra: yaml
Requires-Dist: pyyaml ; extra == 'yaml'
